stat_plot
